micodag/__init__.py
micodag/micpnid.py
micodag-0.0.2.dist-info/LICENSE.txt
micodag-0.0.2.dist-info/METADATA
micodag-0.0.2.dist-info/WHEEL
micodag-0.0.2.dist-info/top_level.txt
micodag-0.0.2.dist-info/RECORD
