Metadata-Version: 2.1
Name: micodag
Version: 0.0.2
Summary: A Python package of mixed integer convex programming for directed acyclic graphs.
Author: Tong Xu
Author-email: tongxu2027@u.northwestern.edu
License: MIT
Keywords: python,Bayesian network
Classifier: Programming Language :: Python :: 3
Classifier: License :: OSI Approved :: MIT License
Requires-Python: >=3.9
License-File: LICENSE.txt
Requires-Dist: gurobipy (>=10.0.0)
Requires-Dist: scipy (>=1.11.1)
Requires-Dist: cvxpy (>=1.3.2)
Requires-Dist: networkx (>=3.0)
Requires-Dist: numpy (>=1.25.0)
